luma.menu-2022.2.post7-py3.9-nspkg.pth
luma/menu/__init__.py
luma/menu/controller.py
luma/menu/controls.py
luma/menu/model.py
luma/menu/userinterface.py
luma/menu/util.py
luma/menu/view.py
luma/menu/devices/__init__.py
luma/menu/devices/adafruit3531.py
luma/menu/fonts/DejaVuSansMono.ttf
luma/menu/fonts/liberation-mono.regular.ttf
luma/menu/widgets/__init__.py
luma/menu/widgets/menu.py
luma/menu/widgets/scrollbar.py
luma/menu/widgets/titlebar.py
luma/menu/widgets/widget.py
luma.menu-2022.2.post7.dist-info/LICENSE
luma.menu-2022.2.post7.dist-info/METADATA
luma.menu-2022.2.post7.dist-info/WHEEL
luma.menu-2022.2.post7.dist-info/namespace_packages.txt
luma.menu-2022.2.post7.dist-info/top_level.txt
luma.menu-2022.2.post7.dist-info/RECORD
